pymanager.py
pymanager-0.2.6.1.dist-info/DESCRIPTION.rst
pymanager-0.2.6.1.dist-info/entry_points.txt
pymanager-0.2.6.1.dist-info/METADATA
pymanager-0.2.6.1.dist-info/metadata.json
pymanager-0.2.6.1.dist-info/RECORD
pymanager-0.2.6.1.dist-info/top_level.txt
pymanager-0.2.6.1.dist-info/WHEEL
pymutils/__init__.py
pymutils/debug.py
pymutils/exited_verifier.py
pymutils/global_storage.py
pymutils/http_service.py
pymutils/http_verifier.py
pymutils/process.py
pymutils/verifier.py
utils/__init__.py
utils/exited_verifier.py
utils/global_storage.py
utils/http_service.py
utils/http_verifier.py
utils/process.py
utils/verifier.py
