Metadata-Version: 2.0
Name: pymanager
Version: 0.2.6.1
Summary: A process manager in Python.
Home-page: https://github.com/baliame/pymanager
Author: Baliame
Author-email: akos.toth@cheppers.com
License: MIT
Keywords: process manager management
Platform: UNKNOWN
Classifier: Development Status :: 3 - Alpha
Classifier: Intended Audience :: Developers
Classifier: Intended Audience :: System Administrators
Classifier: Topic :: Software Development :: Build Tools
Classifier: Topic :: Software Development :: Testing
Classifier: License :: OSI Approved :: MIT License
Classifier: Programming Language :: Python :: 3
Classifier: Programming Language :: Python :: 3.2
Classifier: Programming Language :: Python :: 3.3
Classifier: Programming Language :: Python :: 3.4
Requires-Dist: bottle
Requires-Dist: requests
